keymaster_hjy/__init__.py
keymaster_hjy/_master.py
keymaster_hjy/async_auth_service.py
keymaster_hjy/async_db_init.py
keymaster_hjy/async_integrations.py
keymaster_hjy/async_keys_service.py
keymaster_hjy/async_master.py
keymaster_hjy/async_redis_limiter.py
keymaster_hjy/async_settings_service.py
keymaster_hjy/auth_cache.py
keymaster_hjy/auth_service.py
keymaster_hjy/cli.py
keymaster_hjy/config_provider.py
keymaster_hjy/db_init.py
keymaster_hjy/exceptions.py
keymaster_hjy/integrations.py
keymaster_hjy/keys_service.py
keymaster_hjy/redis_limiter.py
keymaster_hjy/schema.py
keymaster_hjy/settings_service.py
keymaster_hjy/sync_wrapper.py
keymaster_hjy/tags_service.py
keymaster_hjy/utils.py
keymaster_hjy-0.0.1.dist-info/licenses/LICENSE
keymaster_hjy-0.0.1.dist-info/METADATA
keymaster_hjy-0.0.1.dist-info/WHEEL
keymaster_hjy-0.0.1.dist-info/entry_points.txt
keymaster_hjy-0.0.1.dist-info/top_level.txt
keymaster_hjy-0.0.1.dist-info/RECORD
