Metadata-Version: 2.4
Name: keymaster_hjy
Version: 0.0.1
Summary: Zero-config, professional-grade API security manager. Elegant authentication, rate limiting, and audit logging for modern Python APIs.
Author-email: hjy <hjy@example.com>
License: MIT
Project-URL: Homepage, https://github.com/hjy/keymaster_hjy
Project-URL: Repository, https://github.com/hjy/keymaster_hjy.git
Project-URL: Documentation, https://github.com/hjy/keymaster_hjy#readme
Project-URL: Issues, https://github.com/hjy/keymaster_hjy/issues
Project-URL: Changelog, https://github.com/hjy/keymaster_hjy/releases
Keywords: api,authentication,security,rate-limiting,audit-logging,zero-config,fastapi,flask,mysql,redis,async,middleware
Classifier: Development Status :: 4 - Beta
Classifier: Intended Audience :: Developers
Classifier: License :: OSI Approved :: MIT License
Classifier: Operating System :: OS Independent
Classifier: Programming Language :: Python :: 3
Classifier: Programming Language :: Python :: 3.9
Classifier: Programming Language :: Python :: 3.10
Classifier: Programming Language :: Python :: 3.11
Classifier: Programming Language :: Python :: 3.12
Classifier: Framework :: FastAPI
Classifier: Framework :: Flask
Classifier: Topic :: Internet :: WWW/HTTP :: HTTP Servers
Classifier: Topic :: Security
Classifier: Topic :: Software Development :: Libraries :: Python Modules
Classifier: Topic :: System :: Systems Administration :: Authentication/Directory
Classifier: Typing :: Typed
Requires-Python: >=3.9
License-File: LICENSE
Requires-Dist: sqlalchemy[asyncio]>=2.0.0
Requires-Dist: redis[hiredis]>=4.5.0
Requires-Dist: aiomysql>=0.2.0
Requires-Dist: mysql-connector-python
Provides-Extra: test
Requires-Dist: pytest>=7.0.0; extra == "test"
Requires-Dist: pytest-asyncio>=0.21.0; extra == "test"
Requires-Dist: fakeredis[json]>=2.10.0; extra == "test"
Requires-Dist: httpx>=0.24.0; extra == "test"
Provides-Extra: fastapi
Requires-Dist: fastapi>=0.100.0; extra == "fastapi"
Requires-Dist: uvicorn[standard]>=0.20.0; extra == "fastapi"
Provides-Extra: flask
Requires-Dist: flask>=2.0.0; extra == "flask"
Provides-Extra: dev
Requires-Dist: keymaster_hjy[fastapi,flask,test]; extra == "dev"
Requires-Dist: black>=23.0.0; extra == "dev"
Requires-Dist: isort>=5.12.0; extra == "dev"
Requires-Dist: mypy>=1.0.0; extra == "dev"
Requires-Dist: ruff>=0.1.0; extra == "dev"
Provides-Extra: cli
Requires-Dist: click>=8.0.0; extra == "cli"
Provides-Extra: docs
Requires-Dist: sphinx>=7.0.0; extra == "docs"
Requires-Dist: sphinx-rtd-theme>=1.3.0; extra == "docs"
Requires-Dist: sphinx-autodoc-typehints>=1.24.0; extra == "docs"
Requires-Dist: myst-parser>=2.0.0; extra == "docs"
Provides-Extra: all
Requires-Dist: keymaster_hjy[cli,docs,fastapi,flask]; extra == "all"
Dynamic: license-file
